auditwheel_emscripten/__init__.py
auditwheel_emscripten/exports.py
auditwheel_emscripten/function_type.py
auditwheel_emscripten/imports.py
auditwheel_emscripten/lib_utils.py
auditwheel_emscripten/module.py
auditwheel_emscripten/py.typed
auditwheel_emscripten/repair.py
auditwheel_emscripten/show.py
auditwheel_emscripten/wasm_utils.py
auditwheel_emscripten/wheel_utils.py
auditwheel_emscripten/cli/__init__.py
auditwheel_emscripten/cli/main.py
auditwheel_emscripten/emscripten_tools/__init__.py
auditwheel_emscripten/emscripten_tools/diagnostics.py
auditwheel_emscripten/emscripten_tools/utils.py
auditwheel_emscripten/emscripten_tools/webassembly.py
auditwheel_emscripten-0.2.0.dist-info/METADATA
auditwheel_emscripten-0.2.0.dist-info/WHEEL
auditwheel_emscripten-0.2.0.dist-info/entry_points.txt
auditwheel_emscripten-0.2.0.dist-info/licenses/LICENSE
auditwheel_emscripten-0.2.0.dist-info/RECORD
