Metadata-Version: 2.4
Name: auditwheel_emscripten
Version: 0.2.0
Summary: auditwheel-like tool for Pyodide
Project-URL: Home, https://github.com/pyodide/auditwheel-emscripten
Author-email: Gyeongjae Choi <def6488@gmail.com>
License: Mozilla Public License Version 2.0
License-File: LICENSE
Requires-Python: >=3.12
Requires-Dist: leb128
Requires-Dist: packaging
Requires-Dist: pyodide-cli
Requires-Dist: typer
Requires-Dist: wheel
Provides-Extra: test
Requires-Dist: pytest; extra == 'test'
